{
"meta":{"test_sets":[],"test_metrics":[],"learn_metrics":[{"best_value":"Min","name":"RMSE"}],"launch_mode":"Train","parameters":"","iteration_count":100,"learn_sets":["learn"],"name":"experiment"},
"iterations":[
{"learn":[4308.697138],"iteration":0,"passed_time":0.004021586597,"remaining_time":0.3981370731},
{"learn":[4055.391124],"iteration":1,"passed_time":0.008007015003,"remaining_time":0.3923437351},
{"learn":[3819.418616],"iteration":2,"passed_time":0.01188752614,"remaining_time":0.3843633452},
{"learn":[3626.630062],"iteration":3,"passed_time":0.01587451566,"remaining_time":0.3809883759},
{"learn":[3451.783928],"iteration":4,"passed_time":0.01953283587,"remaining_time":0.3711238815},
{"learn":[3333.695362],"iteration":5,"passed_time":0.02335154419,"remaining_time":0.3658408589},
{"learn":[3200.912211],"iteration":6,"passed_time":0.02717424489,"remaining_time":0.3610292535},
{"learn":[3104.242185],"iteration":7,"passed_time":0.03098360152,"remaining_time":0.3563114175},
{"learn":[2987.493109],"iteration":8,"passed_time":0.03468209898,"remaining_time":0.3506745563},
{"learn":[2896.564468],"iteration":9,"passed_time":0.03835421167,"remaining_time":0.3451879051},
{"learn":[2811.371835],"iteration":10,"passed_time":0.04214927739,"remaining_time":0.3410259716},
{"learn":[2751.151617],"iteration":11,"passed_time":0.04654555994,"remaining_time":0.3413341062},
{"learn":[2686.91927],"iteration":12,"passed_time":0.05009323018,"remaining_time":0.3352393097},
{"learn":[2636.008022],"iteration":13,"passed_time":0.05383707582,"remaining_time":0.3307134658},
{"learn":[2588.420118],"iteration":14,"passed_time":0.05753395299,"remaining_time":0.3260257336},
{"learn":[2541.218016],"iteration":15,"passed_time":0.06128659021,"remaining_time":0.3217545986},
{"learn":[2498.897559],"iteration":16,"passed_time":0.06505650111,"remaining_time":0.3176287996},
{"learn":[2463.262764],"iteration":17,"passed_time":0.06864995906,"remaining_time":0.3127387024},
{"learn":[2431.230769],"iteration":18,"passed_time":0.07236962033,"remaining_time":0.3085231183},
{"learn":[2402.10749],"iteration":19,"passed_time":0.07644247618,"remaining_time":0.3057699047},
{"learn":[2380.801639],"iteration":20,"passed_time":0.0802715172,"remaining_time":0.3019738028},
{"learn":[2355.948442],"iteration":21,"passed_time":0.0841976049,"remaining_time":0.298518781},
{"learn":[2335.163301],"iteration":22,"passed_time":0.08802626584,"remaining_time":0.2946966291},
{"learn":[2314.084091],"iteration":23,"passed_time":0.09179336652,"remaining_time":0.290678994},
{"learn":[2297.145041],"iteration":24,"passed_time":0.09538101397,"remaining_time":0.2861430419},
{"learn":[2285.093883],"iteration":25,"passed_time":0.09913022058,"remaining_time":0.2821398586},
{"learn":[2275.034186],"iteration":26,"passed_time":0.1031102986,"remaining_time":0.2787796961},
{"learn":[2259.164498],"iteration":27,"passed_time":0.1070541698,"remaining_time":0.2752821508},
{"learn":[2242.862738],"iteration":28,"passed_time":0.1108035364,"remaining_time":0.2712776236},
{"learn":[2228.668385],"iteration":29,"passed_time":0.114354148,"remaining_time":0.2668263453},
{"learn":[2218.525426],"iteration":30,"passed_time":0.1183691326,"remaining_time":0.2634667789},
{"learn":[2210.655587],"iteration":31,"passed_time":0.1220929746,"remaining_time":0.259447571},
{"learn":[2199.738639],"iteration":32,"passed_time":0.1258782169,"remaining_time":0.2555709252},
{"learn":[2194.348136],"iteration":33,"passed_time":0.1295675727,"remaining_time":0.2515135234},
{"learn":[2183.499219],"iteration":34,"passed_time":0.1332971566,"remaining_time":0.2475518622},
{"learn":[2174.540413],"iteration":35,"passed_time":0.136984622,"remaining_time":0.243528217},
{"learn":[2167.623911],"iteration":36,"passed_time":0.1408184631,"remaining_time":0.2397719777},
{"learn":[2159.272575],"iteration":37,"passed_time":0.1445714104,"remaining_time":0.2358796696},
{"learn":[2154.443384],"iteration":38,"passed_time":0.1483690857,"remaining_time":0.2320644674},
{"learn":[2145.74994],"iteration":39,"passed_time":0.1520556719,"remaining_time":0.2280835078},
{"learn":[2141.791828],"iteration":40,"passed_time":0.1557627,"remaining_time":0.2241463244},
{"learn":[2134.559388],"iteration":41,"passed_time":0.1593643,"remaining_time":0.2200745095},
{"learn":[2131.203897],"iteration":42,"passed_time":0.1629136606,"remaining_time":0.2159553175},
{"learn":[2120.785329],"iteration":43,"passed_time":0.1668712556,"remaining_time":0.212381598},
{"learn":[2116.470864],"iteration":44,"passed_time":0.1704497406,"remaining_time":0.2083274607},
{"learn":[2115.123737],"iteration":45,"passed_time":0.1725763852,"remaining_time":0.2025896696},
{"learn":[2108.819881],"iteration":46,"passed_time":0.1760835778,"remaining_time":0.1985623325},
{"learn":[2105.042654],"iteration":47,"passed_time":0.1799012863,"remaining_time":0.1948930601},
{"learn":[2102.512084],"iteration":48,"passed_time":0.1836459826,"remaining_time":0.191141737},
{"learn":[2096.973604],"iteration":49,"passed_time":0.1876359021,"remaining_time":0.1876359021},
{"learn":[2092.968383],"iteration":50,"passed_time":0.1910879951,"remaining_time":0.1835943482},
{"learn":[2088.112765],"iteration":51,"passed_time":0.1951581396,"remaining_time":0.180145975},
{"learn":[2081.772623],"iteration":52,"passed_time":0.1987753432,"remaining_time":0.1762724742},
{"learn":[2076.105419],"iteration":53,"passed_time":0.2026238469,"remaining_time":0.1726054992},
{"learn":[2072.078591],"iteration":54,"passed_time":0.2063781745,"remaining_time":0.16885487},
{"learn":[2068.588874],"iteration":55,"passed_time":0.2101944649,"remaining_time":0.1651527938},
{"learn":[2066.472039],"iteration":56,"passed_time":0.2139875477,"remaining_time":0.1614292027},
{"learn":[2062.91056],"iteration":57,"passed_time":0.2176795546,"remaining_time":0.1576300223},
{"learn":[2060.049457],"iteration":58,"passed_time":0.2211495608,"remaining_time":0.1536802032},
{"learn":[2056.160951],"iteration":59,"passed_time":0.2250261506,"remaining_time":0.1500174338},
{"learn":[2053.969702],"iteration":60,"passed_time":0.2287418912,"remaining_time":0.1462448157},
{"learn":[2046.928073],"iteration":61,"passed_time":0.2325106113,"remaining_time":0.1425065037},
{"learn":[2043.746412],"iteration":62,"passed_time":0.2361952171,"remaining_time":0.1387178259},
{"learn":[2041.777113],"iteration":63,"passed_time":0.239836524,"remaining_time":0.1349080447},
{"learn":[2039.745725],"iteration":64,"passed_time":0.2437800557,"remaining_time":0.1312661838},
{"learn":[2038.955043],"iteration":65,"passed_time":0.2455630869,"remaining_time":0.1265021963},
{"learn":[2036.140202],"iteration":66,"passed_time":0.2492321396,"remaining_time":0.1227561285},
{"learn":[2034.88245],"iteration":67,"passed_time":0.2528112455,"remaining_time":0.1189699979},
{"learn":[2031.816163],"iteration":68,"passed_time":0.2566379155,"remaining_time":0.1153010925},
{"learn":[2029.706137],"iteration":69,"passed_time":0.2604470129,"remaining_time":0.1116201484},
{"learn":[2025.533258],"iteration":70,"passed_time":0.2638748124,"remaining_time":0.1077798529},
{"learn":[2022.044608],"iteration":71,"passed_time":0.2674510169,"remaining_time":0.1040087288},
{"learn":[2020.028626],"iteration":72,"passed_time":0.2712863396,"remaining_time":0.1003387832},
{"learn":[2017.88362],"iteration":73,"passed_time":0.2747520851,"remaining_time":0.09653451639},
{"learn":[2013.246206],"iteration":74,"passed_time":0.2785851463,"remaining_time":0.09286171543},
{"learn":[2009.513872],"iteration":75,"passed_time":0.2823448948,"remaining_time":0.08916154572},
{"learn":[2006.722748],"iteration":76,"passed_time":0.2860566446,"remaining_time":0.08544549126},
{"learn":[2002.95786],"iteration":77,"passed_time":0.2900378137,"remaining_time":0.08180553719},
{"learn":[1998.040266],"iteration":78,"passed_time":0.2937685564,"remaining_time":0.07809037575},
{"learn":[1996.118447],"iteration":79,"passed_time":0.2972498055,"remaining_time":0.07431245137},
{"learn":[1994.854552],"iteration":80,"passed_time":0.3010736956,"remaining_time":0.07062222488},
{"learn":[1991.188748],"iteration":81,"passed_time":0.3044866915,"remaining_time":0.06683854204},
{"learn":[1986.814258],"iteration":82,"passed_time":0.3081758164,"remaining_time":0.06312034794},
{"learn":[1985.442781],"iteration":83,"passed_time":0.311730948,"remaining_time":0.05937732343},
{"learn":[1982.860258],"iteration":84,"passed_time":0.3154218749,"remaining_time":0.05566268381},
{"learn":[1981.431694],"iteration":85,"passed_time":0.319444891,"remaining_time":0.05200265667},
{"learn":[1978.544445],"iteration":86,"passed_time":0.3234971914,"remaining_time":0.04833866079},
{"learn":[1973.19115],"iteration":87,"passed_time":0.3275707574,"remaining_time":0.04466873965},
{"learn":[1970.728857],"iteration":88,"passed_time":0.3313201346,"remaining_time":0.04094967956},
{"learn":[1969.051881],"iteration":89,"passed_time":0.3351239605,"remaining_time":0.03723599561},
{"learn":[1964.92755],"iteration":90,"passed_time":0.3394900985,"remaining_time":0.0335759438},
{"learn":[1963.005934],"iteration":91,"passed_time":0.3434159675,"remaining_time":0.02986225804},
{"learn":[1960.115281],"iteration":92,"passed_time":0.3470929805,"remaining_time":0.0261252781},
{"learn":[1956.873975],"iteration":93,"passed_time":0.3508426478,"remaining_time":0.02239421156},
{"learn":[1954.86521],"iteration":94,"passed_time":0.3544096309,"remaining_time":0.01865313847},
{"learn":[1952.539354],"iteration":95,"passed_time":0.357967323,"remaining_time":0.01491530512},
{"learn":[1949.318048],"iteration":96,"passed_time":0.3615908669,"remaining_time":0.01118322269},
{"learn":[1944.994541],"iteration":97,"passed_time":0.3653386541,"remaining_time":0.0074558909},
{"learn":[1942.867354],"iteration":98,"passed_time":0.3690943419,"remaining_time":0.003728225676},
{"learn":[1941.351029],"iteration":99,"passed_time":0.372939655,"remaining_time":0}
]}